influxdb_cli/__init__.py
influxdb_cli/influx3.py
pyinflux3_cli-0.9.2.data/data/influx3/influx3.py
pyinflux3_cli-0.9.2.dist-info/METADATA
pyinflux3_cli-0.9.2.dist-info/WHEEL
pyinflux3_cli-0.9.2.dist-info/entry_points.txt
pyinflux3_cli-0.9.2.dist-info/top_level.txt
pyinflux3_cli-0.9.2.dist-info/RECORD
